{
	"configurations" : 
	[
		{
			"directories" : 
			[
				{
					"build" : ".",
					"childIndexes" : 
					[
						1,
						2,
						3,
						4,
						5,
						6,
						7,
						8
					],
					"minimumCMakeVersion" : 
					{
						"string" : "3.20"
					},
					"projectIndex" : 0,
					"source" : ".",
					"targetIndexes" : 
					[
						7
					]
				},
				{
					"build" : "assignment_1",
					"minimumCMakeVersion" : 
					{
						"string" : "3.20"
					},
					"parentIndex" : 0,
					"projectIndex" : 1,
					"source" : "assignment_1",
					"targetIndexes" : 
					[
						6
					]
				},
				{
					"build" : "HW2",
					"minimumCMakeVersion" : 
					{
						"string" : "3.20"
					},
					"parentIndex" : 0,
					"projectIndex" : 2,
					"source" : "HW2",
					"targetIndexes" : 
					[
						0
					]
				},
				{
					"build" : "HW3",
					"minimumCMakeVersion" : 
					{
						"string" : "3.20"
					},
					"parentIndex" : 0,
					"projectIndex" : 3,
					"source" : "HW3",
					"targetIndexes" : 
					[
						1
					]
				},
				{
					"build" : "HW4",
					"minimumCMakeVersion" : 
					{
						"string" : "3.20"
					},
					"parentIndex" : 0,
					"projectIndex" : 4,
					"source" : "HW4",
					"targetIndexes" : 
					[
						2
					]
				},
				{
					"build" : "HW5",
					"minimumCMakeVersion" : 
					{
						"string" : "3.20"
					},
					"parentIndex" : 0,
					"projectIndex" : 5,
					"source" : "HW5",
					"targetIndexes" : 
					[
						3
					]
				},
				{
					"build" : "HW6",
					"minimumCMakeVersion" : 
					{
						"string" : "3.20"
					},
					"parentIndex" : 0,
					"projectIndex" : 6,
					"source" : "HW6",
					"targetIndexes" : 
					[
						4
					]
				},
				{
					"build" : "Pro1",
					"minimumCMakeVersion" : 
					{
						"string" : "3.20"
					},
					"parentIndex" : 0,
					"projectIndex" : 7,
					"source" : "Pro1",
					"targetIndexes" : 
					[
						8
					]
				},
				{
					"build" : "Pro2",
					"minimumCMakeVersion" : 
					{
						"string" : "3.20"
					},
					"parentIndex" : 0,
					"projectIndex" : 8,
					"source" : "Pro2",
					"targetIndexes" : 
					[
						5
					]
				}
			],
			"name" : "Debug",
			"projects" : 
			[
				{
					"childIndexes" : 
					[
						1,
						2,
						3,
						4,
						5,
						6,
						7,
						8
					],
					"directoryIndexes" : 
					[
						0
					],
					"name" : "course_3",
					"targetIndexes" : 
					[
						7
					]
				},
				{
					"directoryIndexes" : 
					[
						1
					],
					"name" : "assignment_1",
					"parentIndex" : 0,
					"targetIndexes" : 
					[
						6
					]
				},
				{
					"directoryIndexes" : 
					[
						2
					],
					"name" : "HW2",
					"parentIndex" : 0,
					"targetIndexes" : 
					[
						0
					]
				},
				{
					"directoryIndexes" : 
					[
						3
					],
					"name" : "HW3",
					"parentIndex" : 0,
					"targetIndexes" : 
					[
						1
					]
				},
				{
					"directoryIndexes" : 
					[
						4
					],
					"name" : "HW4",
					"parentIndex" : 0,
					"targetIndexes" : 
					[
						2
					]
				},
				{
					"directoryIndexes" : 
					[
						5
					],
					"name" : "HW5",
					"parentIndex" : 0,
					"targetIndexes" : 
					[
						3
					]
				},
				{
					"directoryIndexes" : 
					[
						6
					],
					"name" : "HW6",
					"parentIndex" : 0,
					"targetIndexes" : 
					[
						4
					]
				},
				{
					"directoryIndexes" : 
					[
						7
					],
					"name" : "HW3",
					"parentIndex" : 0,
					"targetIndexes" : 
					[
						8
					]
				},
				{
					"directoryIndexes" : 
					[
						8
					],
					"name" : "PR2",
					"parentIndex" : 0,
					"targetIndexes" : 
					[
						5
					]
				}
			],
			"targets" : 
			[
				{
					"directoryIndex" : 2,
					"id" : "HW2::@55324602d6d7b2a5aefb",
					"jsonFile" : "target-HW2-Debug-aef8d0da241bf892f774.json",
					"name" : "HW2",
					"projectIndex" : 2
				},
				{
					"directoryIndex" : 3,
					"id" : "HW3::@2f3407f06ca23028a016",
					"jsonFile" : "target-HW3-Debug-d84af62ec2a44cc5cf4a.json",
					"name" : "HW3",
					"projectIndex" : 3
				},
				{
					"directoryIndex" : 4,
					"id" : "HW4::@8fcb141de1421edafaf3",
					"jsonFile" : "target-HW4-Debug-bd64fe01f83d2e507d39.json",
					"name" : "HW4",
					"projectIndex" : 4
				},
				{
					"directoryIndex" : 5,
					"id" : "HW5::@3eeabb411410a5edd744",
					"jsonFile" : "target-HW5-Debug-ce8d0641186e571d2853.json",
					"name" : "HW5",
					"projectIndex" : 5
				},
				{
					"directoryIndex" : 6,
					"id" : "HW6::@7bc310d91b49ebc1aa04",
					"jsonFile" : "target-HW6-Debug-11016bba2806454f5a98.json",
					"name" : "HW6",
					"projectIndex" : 6
				},
				{
					"directoryIndex" : 8,
					"id" : "Pro2::@86b75f1b0149a90d3764",
					"jsonFile" : "target-Pro2-Debug-83e6aeead03b405437dc.json",
					"name" : "Pro2",
					"projectIndex" : 8
				},
				{
					"directoryIndex" : 1,
					"id" : "assignment_1::@fa38754c8d7a7c62b901",
					"jsonFile" : "target-assignment_1-Debug-a35e7712677f3345a8f7.json",
					"name" : "assignment_1",
					"projectIndex" : 1
				},
				{
					"directoryIndex" : 0,
					"id" : "course_3::@6890427a1f51a3e7e1df",
					"jsonFile" : "target-course_3-Debug-a8c5e19e3f59d3b3e50c.json",
					"name" : "course_3",
					"projectIndex" : 0
				},
				{
					"directoryIndex" : 7,
					"id" : "project1::@f7e97e38ed61423f2a6e",
					"jsonFile" : "target-project1-Debug-49ca5f8ce3cca1150dd0.json",
					"name" : "project1",
					"projectIndex" : 7
				}
			]
		}
	],
	"kind" : "codemodel",
	"paths" : 
	{
		"build" : "C:/Users/james/CLionProjects/course_3/out/build/x64-Debug",
		"source" : "C:/Users/james/CLionProjects/course_3"
	},
	"version" : 
	{
		"major" : 2,
		"minor" : 2
	}
}
